zarinpal.py
errors/ResponseException.py
errors/__init__.py
remino_zarinpal_py_sdk-1.0.3.dist-info/licenses/LICENSE
resources/Inquiries.py
resources/Payments.py
resources/Refunds.py
resources/Reverses.py
resources/Transactions.py
resources/Unverified.py
resources/Verifications.py
resources/__init__.py
tools/Config.py
tools/Validator.py
tools/__init__.py
remino_zarinpal_py_sdk-1.0.3.dist-info/METADATA
remino_zarinpal_py_sdk-1.0.3.dist-info/WHEEL
remino_zarinpal_py_sdk-1.0.3.dist-info/top_level.txt
remino_zarinpal_py_sdk-1.0.3.dist-info/RECORD
