Metadata-Version: 2.4
Name: remino-zarinpal-py-sdk
Version: 1.0.3
Summary: A Python SDK for Remino Zarinpal Payment Gateway
Home-page: https://github.com/reminerdino/remino-zarinpal-py-sdk
Author: Iman Ashoori
Author-email: imanashoorii.77@gmail.com
Classifier: Programming Language :: Python :: 3
Classifier: License :: OSI Approved :: MIT License
Classifier: Operating System :: OS Independent
Requires-Python: >=3.10
License-File: LICENSE
Requires-Dist: anyio==4.7.0
Requires-Dist: attrs==24.2.0
Requires-Dist: certifi==2024.8.30
Requires-Dist: cffi==1.17.1
Requires-Dist: charset-normalizer==3.3.2
Requires-Dist: chromedriver-autoinstaller==0.6.4
Requires-Dist: colorama==0.4.6
Requires-Dist: crypto==1.4.1
Requires-Dist: cryptography==43.0.1
Requires-Dist: dnspython==2.7.0
Requires-Dist: docutils==0.21.2
Requires-Dist: email_validator==2.2.0
Requires-Dist: h11==0.14.0
Requires-Dist: httpcore==1.0.7
Requires-Dist: httpx==0.28.1
Requires-Dist: idna==3.10
Requires-Dist: iniconfig==2.0.0
Requires-Dist: jaraco.classes==3.4.0
Requires-Dist: jaraco.context==6.0.1
Requires-Dist: jaraco.functools==4.1.0
Requires-Dist: jsonschema==4.23.0
Requires-Dist: jsonschema-specifications==2024.10.1
Requires-Dist: keyring==25.6.0
Requires-Dist: markdown-it-py==3.0.0
Requires-Dist: mdurl==0.1.2
Requires-Dist: more-itertools==10.5.0
Requires-Dist: Naked==0.1.32
Requires-Dist: nh3==0.2.20
Requires-Dist: outcome==1.3.0.post0
Requires-Dist: packaging==24.2
Requires-Dist: pkginfo==1.12.0
Requires-Dist: pluggy==1.5.0
Requires-Dist: psutil==6.1.0
Requires-Dist: pycparser==2.22
Requires-Dist: pycryptodome==3.21.0
Requires-Dist: Pygments==2.19.1
Requires-Dist: pyotp==2.9.0
Requires-Dist: pyperclip==1.9.0
Requires-Dist: PySocks==1.7.1
Requires-Dist: pytest==8.3.4
Requires-Dist: pytest-order==1.3.0
Requires-Dist: python-dotenv==1.0.1
Requires-Dist: PyYAML==6.0.2
Requires-Dist: readme_renderer==44.0
Requires-Dist: referencing==0.35.1
Requires-Dist: requests==2.32.3
Requires-Dist: requests-mock==1.12.1
Requires-Dist: requests-pkcs12==1.25
Requires-Dist: requests-toolbelt==1.0.0
Requires-Dist: responses==0.25.3
Requires-Dist: rfc3986==2.0.0
Requires-Dist: rich==13.9.4
Requires-Dist: rpds-py==0.20.0
Requires-Dist: selenium==4.27.1
Requires-Dist: setuptools==75.8.0
Requires-Dist: shellescape==3.8.1
Requires-Dist: sniffio==1.3.1
Requires-Dist: sortedcontainers==2.4.0
Requires-Dist: trio==0.27.0
Requires-Dist: trio-websocket==0.11.1
Requires-Dist: twine==6.0.1
Requires-Dist: typing_extensions==4.12.2
Requires-Dist: urllib3==2.2.3
Requires-Dist: webdriver-manager==4.0.2
Requires-Dist: websocket-client==1.8.0
Requires-Dist: wheel==0.45.1
Requires-Dist: wsproto==1.2.0
Dynamic: author
Dynamic: author-email
Dynamic: classifier
Dynamic: description
Dynamic: description-content-type
Dynamic: home-page
Dynamic: license-file
Dynamic: requires-dist
Dynamic: requires-python
Dynamic: summary
